HelloWorld/HelloWorld.py
HelloWorld/__init__.py
libre_helloworld-0.2.dist-info/METADATA
libre_helloworld-0.2.dist-info/WHEEL
libre_helloworld-0.2.dist-info/top_level.txt
libre_helloworld-0.2.dist-info/RECORD
