Metadata-Version: 2.1
Name: libre-helloworld
Version: 0.2
Summary: Print using HelloWorld
Home-page: https://github.com/therandomspoon/HelloWorld
Author: Therandomspoon
Author-email: admin@randspoon.co.uk
Classifier: Programming Language :: Python :: 3
Classifier: License :: OSI Approved :: GNU General Public License v3 (GPLv3)
Requires-Python: >=3.6
